caz/__init__.py
caz/__main__.py
caz/app.py
caz/async_utils.py
caz/bitboard_utils.py
caz/cli.py
caz/graph.py
caz/kaggle_sandbox.py
caz/kaggle_types.py
caz/alpha_zero/__init__.py
caz/alpha_zero/alpha_zero.py
caz/alpha_zero/alpha_zero_mcts.py
caz/alpha_zero/alpha_zero_parameters.py
caz/alpha_zero/alpha_zero_training_models.py
caz/alpha_zero/network.py
caz/alpha_zero/network_torch.py
caz/alpha_zero/retrainer.py
caz/alpha_zero/supervised_learning.py
caz/games/__init__.py
caz/games/game.py
caz/games/game_type.py
caz/images/__init__.py
caz/images/black-bishop.png
caz/images/black-king.png
caz/images/black-knight.png
caz/images/black-pawn.png
caz/images/black-queen.png
caz/images/black-rook.png
caz/images/caz_flat_logo.png
caz/images/caz_splashscreen.jpg
caz/images/tiny_chess.ico
caz/images/white-bishop.png
caz/images/white-king.png
caz/images/white-knight.png
caz/images/white-pawn.png
caz/images/white-queen.png
caz/images/white-rook.png
caz/solvers/__init__.py
caz/solvers/agent_type.py
caz/solvers/mcts.py
caz/solvers/minimax.py
caz/solvers/solver.py
caz/states/__init__.py
caz/states/chess.py
caz/states/chess_enums.py
caz/states/connectx.py
caz/states/state.py
caz/states/tictactoe.py
caz/views/__init__.py
caz/views/chess_detail.py
caz/views/chess_main.py
caz/views/console.py
caz/views/html.py
caz/views/plot.py
caz/views/policies.py
caz/views/view.py
catchem_alpha_zero-0.0.4.dist-info/LICENSE
catchem_alpha_zero-0.0.4.dist-info/METADATA
catchem_alpha_zero-0.0.4.dist-info/WHEEL
catchem_alpha_zero-0.0.4.dist-info/entry_points.txt
catchem_alpha_zero-0.0.4.dist-info/top_level.txt
catchem_alpha_zero-0.0.4.dist-info/RECORD
