Metadata-Version: 2.1
Name: catchem-alpha-zero
Version: 0.0.4
Summary: CatchemAlphaZero: AI techniques for solving games
Home-page: https://github.com/CatchemAL/CatchemAlphaZero
Author: Alex Cross
Author-email: AlexJCross90@gmail.com
Project-URL: Bug Tracker, https://github.com/CatchemAL/CatchemAlphaZero/issues
Classifier: Programming Language :: Python
Classifier: Programming Language :: Python :: 3
Classifier: Programming Language :: Python :: 3 :: Only
Classifier: Programming Language :: Python :: 3.11
Classifier: License :: OSI Approved :: MIT License
Classifier: Operating System :: OS Independent
Requires-Python: >=3.10
License-File: LICENSE
Requires-Dist: numpy
Requires-Dist: torch
Requires-Dist: torchvision
Requires-Dist: tensorboard
Requires-Dist: matplotlib
Requires-Dist: ipywidgets
Requires-Dist: jupyterlab
Requires-Dist: nest-asyncio
Requires-Dist: tqdm
Requires-Dist: chess
Requires-Dist: colorama
Requires-Dist: graphviz
Requires-Dist: kaggle-environments
Provides-Extra: dev
Requires-Dist: black ; extra == 'dev'
Requires-Dist: flake8 ; extra == 'dev'
Requires-Dist: isort ; extra == 'dev'
Requires-Dist: mypy ; extra == 'dev'
Requires-Dist: pytest ; extra == 'dev'
